{
  "ok": true,
  "updated_at": "2026-06-09T12:06:20.245061Z",
  "playlist_id": "PLit3sD3SUfXVOB41L0JEae6LNTZtrg58n",
  "playlist_title": "Twelve Dollars",
  "playlist_url": "https://www.youtube.com/playlist?list=PLit3sD3SUfXVOB41L0JEae6LNTZtrg58n",
  "removed_items": 8,
  "inserted_items": 8,
  "verified_items": 8,
  "tracks": [
    {
      "track": 1,
      "title": "Brain Rot",
      "video_id": "U7aczBSruAY",
      "url": "https://youtu.be/U7aczBSruAY"
    },
    {
      "track": 2,
      "title": "Every Pearl in Carmel",
      "video_id": "QodRYnvTVZc",
      "url": "https://youtu.be/QodRYnvTVZc"
    },
    {
      "track": 3,
      "title": "The Other One's Charging",
      "video_id": "EprgLKHp-lE",
      "url": "https://youtu.be/EprgLKHp-lE"
    },
    {
      "track": 4,
      "title": "Twelve Dollars",
      "video_id": "G2RlCwZKOsk",
      "url": "https://youtu.be/G2RlCwZKOsk"
    },
    {
      "track": 5,
      "title": "William and Dander",
      "video_id": "qjh8DUlg5UU",
      "url": "https://youtu.be/qjh8DUlg5UU"
    },
    {
      "track": 6,
      "title": "Just Don't Talk About It",
      "video_id": "3M0CvX5BRrA",
      "url": "https://youtu.be/3M0CvX5BRrA"
    },
    {
      "track": 7,
      "title": "Gluten Free Bread",
      "video_id": "ajN3i75Sc74",
      "url": "https://youtu.be/ajN3i75Sc74"
    },
    {
      "track": 8,
      "title": "When Lily Talks",
      "video_id": "xp3DAk8RphU",
      "url": "https://youtu.be/xp3DAk8RphU"
    }
  ],
  "current_playlist_order": [
    {
      "position": 0,
      "video_id": "U7aczBSruAY",
      "title": "Brain Rot - Lily Roo"
    },
    {
      "position": 1,
      "video_id": "QodRYnvTVZc",
      "title": "Every Pearl in Carmel - Lily Roo"
    },
    {
      "position": 2,
      "video_id": "EprgLKHp-lE",
      "title": "The Other One's Charging - Lily Roo"
    },
    {
      "position": 3,
      "video_id": "G2RlCwZKOsk",
      "title": "Twelve Dollars - Lily Roo"
    },
    {
      "position": 4,
      "video_id": "qjh8DUlg5UU",
      "title": "William and Dander - Lily Roo"
    },
    {
      "position": 5,
      "video_id": "3M0CvX5BRrA",
      "title": "Just Don't Talk About It - Lily Roo"
    },
    {
      "position": 6,
      "video_id": "ajN3i75Sc74",
      "title": "Gluten Free Bread - Lily Roo"
    },
    {
      "position": 7,
      "video_id": "xp3DAk8RphU",
      "title": "When Lily Talks - Lily Roo"
    }
  ]
}
