{
  "ok": false,
  "updated_at": "2026-06-20T09:36:32.797725Z",
  "source": "public-web-search-plus-spotify-oembed",
  "query_artist": "Lily Roo",
  "query_title": "Analog Myth",
  "release_url": "",
  "album_id": "",
  "artist_url": "",
  "title": "",
  "candidate_urls": [],
  "candidate_count": 0,
  "candidates": [],
  "search_attempts": [
    {
      "query": "site:open.spotify.com/album \"Analog Myth\" \"Lily Roo\"",
      "endpoint": "https://lite.duckduckgo.com/lite/",
      "http_status": 202,
      "error": "",
      "candidate_count": 0,
      "request_timeout_seconds": 5
    },
    {
      "query": "site:open.spotify.com/album \"Analog Myth\" \"Lily Roo\"",
      "endpoint": "https://html.duckduckgo.com/html/",
      "http_status": 202,
      "error": "",
      "candidate_count": 0,
      "request_timeout_seconds": 5
    },
    {
      "query": "\"Analog Myth\" \"Lily Roo\" \"open.spotify.com/album\"",
      "endpoint": "https://lite.duckduckgo.com/lite/",
      "http_status": 202,
      "error": "",
      "candidate_count": 0,
      "request_timeout_seconds": 5
    },
    {
      "query": "\"Analog Myth\" \"Lily Roo\" \"open.spotify.com/album\"",
      "endpoint": "https://html.duckduckgo.com/html/",
      "http_status": 202,
      "error": "",
      "candidate_count": 0,
      "request_timeout_seconds": 5
    }
  ],
  "action_needed": "Spotify album not found for Lily Roo - Analog Myth. Re-run after DistroKid exposes the public release."
}
